[
  {
    "name": "Akeso Inc",
    "sector_code": 54,
    "co2_revenues": 4.983699,
    "water_revenues": 397.756274,
    "energy_revenues": 80.745970,
    "health_policy": false,
    "supply_chain_policy": false,
    "diversity_policy": true,
    "salary_gap": 29.542590,
    "net_employment_creation": 23.298969,
    "board_independency_policy": true,
    "board_diversity_policy": true,
    "board_experience_policy": true,
    "renewable_energy": 1.101125e+05,
    "market_gap": 2.159120e+09,
    "green_capex": false,
    "date": "2023-01-15"
  },
  {
    "name": "Akeso Inc",
    "sector_code": 54,
    "co2_revenues": 4.983699,
    "water_revenues": 450.983456,
    "energy_revenues": 91.551281,
    "health_policy": true,
    "supply_chain_policy": false,
    "diversity_policy": true,
    "salary_gap": 15.081980,
    "net_employment_creation": -0.256410,
    "board_independency_policy": true,
    "board_diversity_policy": true,
    "board_experience_policy": true,
    "renewable_energy": 1.248476e+05,
    "market_gap": 2.448050e+09,
    "green_capex": false,
    "date": "2023-04-25"
  },
  {
    "name": "Akeso Inc",
    "sector_code": 54,
    "co2_revenues": 0.805612,
    "water_revenues": 363.882420,
    "energy_revenues": 73.869454,
    "health_policy": false,
    "supply_chain_policy": false,
    "diversity_policy": true,
    "salary_gap": 12.169110,
    "net_employment_creation": 2.719033,
    "board_independency_policy": true,
    "board_diversity_policy": true,
    "board_experience_policy": true,
    "renewable_energy": 1.007351e+05,
    "market_gap": 1.975244e+09,
    "green_capex": false,
    "date": "2022-01-12"
  },
  {
    "name": "Akeso Inc",
    "sector_code": 54,
    "co2_revenues": 6.506291,
    "water_revenues": 190.927226,
    "energy_revenues": 38.758921,
    "health_policy": true,
    "supply_chain_policy": false,
    "diversity_policy": true,
    "salary_gap": 6.385069,
    "net_employment_creation": 0.000000,
    "board_independency_policy": true,
    "board_diversity_policy": true,
    "board_experience_policy": true,
    "renewable_energy": 5.285517e+04,
    "market_gap": 1.036400e+09,
    "green_capex": false,
    "date": "2023-02-25"
  },
  {
    "name": "Akeso Inc",
    "sector_code": 54,
    "co2_revenues": 2.668156,
    "water_revenues": 44.362039,
    "energy_revenues": 76.016740,
    "health_policy": true,
    "supply_chain_policy": false,
    "diversity_policy": true,
    "salary_gap": 14.466792,
    "net_employment_creation": 27.299367,
    "board_independency_policy": true,
    "board_diversity_policy": true,
    "board_experience_policy": true,
    "renewable_energy": 3.868170e+04,
    "market_gap": 5.517225e+09,
    "green_capex": true,
    "date": "2021-03-08"
  },
  {
    "name": "Akeso Inc",
    "sector_code": 54,
    "co2_revenues": 9.375163,
    "water_revenues": 1095.149597,
    "energy_revenues": 222.319350,
    "health_policy": false,
    "supply_chain_policy": false,
    "diversity_policy": true,
    "salary_gap": 136.339687,
    "net_employment_creation": 16.717325,
    "board_independency_policy": true,
    "board_diversity_policy": false,
    "board_experience_policy": false,
    "renewable_energy": 3.031748e+05,
    "market_gap": 5.944744e+09,
    "green_capex": false,
    "date": "2024-04-09"
  },
  {
    "name": "Akeso Inc",
    "sector_code": 54,
    "co2_revenues": 0.655802,
    "water_revenues": 45.946290,
    "energy_revenues": 68.259398,
    "health_policy": true,
    "supply_chain_policy": true,
    "diversity_policy": true,
    "salary_gap": 31.383552,
    "net_employment_creation": 21.390374,
    "board_independency_policy": true,
    "board_diversity_policy": true,
    "board_experience_policy": true,
    "renewable_energy": 3.005530e+03,
    "market_gap": 5.094060e+09,
    "green_capex": false,
    "date": "2020-05-03"
  },
  {
    "name": "Akeso Inc",
    "sector_code": 54,
    "co2_revenues": 3.409374,
    "water_revenues": 2774.413798,
    "energy_revenues": 563.216088,
    "health_policy": true,
    "supply_chain_policy": true,
    "diversity_policy": true,
    "salary_gap": 586.842385,
    "net_employment_creation": 27.065192,
    "board_independency_policy": true,
    "board_diversity_policy": true,
    "board_experience_policy": true,
    "renewable_energy": 4.967820e+04,
    "market_gap": 1.506021e+10,
    "green_capex": false,
    "date": "2023-06-27"
  },
  {
    "name": "Akeso Inc",
    "sector_code": 54,
    "co2_revenues": 1.373972,
    "water_revenues": 6776.805551,
    "energy_revenues": 1375.716166,
    "health_policy": true,
    "supply_chain_policy": false,
    "diversity_policy": true,
    "salary_gap": 226.632799,
    "net_employment_creation": -6.739726,
    "board_independency_policy": true,
    "board_diversity_policy": true,
    "board_experience_policy": true,
    "renewable_energy": 1.876051e+06,
    "market_gap": 3.678618e+10,
    "green_capex": false,
    "date": "2022-07-15"
  },
  {
    "name": "Akeso Inc",
    "sector_code": 54,
    "co2_revenues": 0.293606,
    "water_revenues": 8.993134,
    "energy_revenues": 24.163635,
    "health_policy": true,
    "supply_chain_policy": true,
    "diversity_policy": true,
    "salary_gap": 13.770490,
    "net_employment_creation": -1.578947,
    "board_independency_policy": true,
    "board_diversity_policy": true,
    "board_experience_policy": true,
    "renewable_energy": 7.819366e+04,
    "market_gap": 1.533245e+09,
    "green_capex": false,
    "date": "2021-08-23"
  }
]